{"PageType":"Categories","HeaderCategoryLabel":"Category","SearchAPI":"","PageName":"Economics","Categories":["Agriculture","Demographics","Earth Science","Geography","Government","Health","Healthcare","History","Human Activities","Medicine","Politics","Sociology","Statistics","Transportation"],"CategoryDisplayLabel":"Categories","Resources":[{"Name":{"Label":"British Coal Mining Disaster Data","URL":"https:\/\/datarepository.wolframcloud.com\/resources\/0579dba5-a7d9-4873-8a72-a39276862751\/"},"UUID":"0579dba5-a7d9-4873-8a72-a39276862751","Description":"British coal mine disaster data by year for the years 1851-1962","ReleaseDate":"2022-10-14","Score":"Missing","FilterCategories":["Economics","Statistics"],"Status":"","SubResources":[],"Icons":[]},{"Name":{"Label":"California Urban Water Supplier Monitoring Reports","URL":"https:\/\/datarepository.wolframcloud.com\/resources\/f1513113-6a2b-41be-97d6-79a89de8e6ab\/"},"UUID":"f1513113-6a2b-41be-97d6-79a89de8e6ab","Description":"Monthly reports of the larger urban water suppliers in California on water production and conservation activities, from the State of California's Drinking Water Information Clearinghouse (DRINC)","ReleaseDate":"2018-07-16","Score":"Missing","FilterCategories":["Agriculture","Economics","Government","Health"],"Status":"","SubResources":[],"Icons":[]},{"Name":{"Label":"Coronavirus COVID-19 Pandemic Government Measures","URL":"https:\/\/datarepository.wolframcloud.com\/resources\/51d1545a-614f-4b18-8a81-ca72189a986f\/"},"UUID":"51d1545a-614f-4b18-8a81-ca72189a986f","Description":"Measures taken by governments from different countries to fight the coronavirus COVID-19 pandemic caused by the SARS-CoV-2","ReleaseDate":"2020-04-09","Score":"Missing","FilterCategories":["Demographics","Economics","Geography","Government","Health","Healthcare","Medicine","Politics","Statistics"],"Status":"","SubResources":[],"Icons":[]},{"Name":{"Label":"Danish Fire Insurance Claims","URL":"https:\/\/datarepository.wolframcloud.com\/resources\/4deb3a67-d305-41c5-aa63-3e5175b36a2d\/"},"UUID":"4deb3a67-d305-41c5-aa63-3e5175b36a2d","Description":"Fire insurance claims in Denmark from Thursday 3rd January 1980 until Monday 31st December 1990","ReleaseDate":"2022-09-19","Score":"Missing","FilterCategories":["Economics","Statistics"],"Status":"","SubResources":[],"Icons":[]},{"Name":{"Label":"Data for Maymin & Langer (2021) \"Cognitive Biases and Mindfulness\"","URL":"https:\/\/datarepository.wolframcloud.com\/resources\/1ad960b4-04b4-4a2f-8763-86de337de18b\/"},"UUID":"1ad960b4-04b4-4a2f-8763-86de337de18b","Description":"Survey data generated and analysed in the article \"Cognitive Biases and Mindfulness\" by Philip Z. Maymin and Ellen J. Langer in the Nature journal Humanities and Social Sciences Communications","ReleaseDate":"2020-12-24","Score":"Missing","FilterCategories":["Economics","Human Activities"],"Status":"","SubResources":[],"Icons":[]},{"Name":{"Label":"Detailed Average Prices of Consumer Goods in Europe","URL":"https:\/\/datarepository.wolframcloud.com\/resources\/3a41e326-48d7-4eaa-b9c8-dafd458a8f71\/"},"UUID":"3a41e326-48d7-4eaa-b9c8-dafd458a8f71","Description":"Average prices per country of well-defined consumer goods and services","ReleaseDate":"2015-10-15","Score":"Missing","FilterCategories":["Economics"],"Status":"","SubResources":[],"Icons":[]},{"Name":{"Label":"FDIC Institution EntityStore","URL":"https:\/\/datarepository.wolframcloud.com\/resources\/6f5d37d4-1406-483c-b67c-f58d903d16b1\/"},"UUID":"6f5d37d4-1406-483c-b67c-f58d903d16b1","Description":"A Wolfram Language EntityStore with selected data on FDIC insured institutions","ReleaseDate":"2016-07-19","Score":"Missing","FilterCategories":["Economics"],"Status":"","SubResources":[],"Icons":[]},{"Name":{"Label":"HUD Location Affordability Index","URL":"https:\/\/datarepository.wolframcloud.com\/resources\/0e4fcfc5-0540-48c1-ad7e-08c5c8ce2fdd\/"},"UUID":"0e4fcfc5-0540-48c1-ad7e-08c5c8ce2fdd","Description":"Data on family income and costs of housing and transportion in U.S. cities","ReleaseDate":"2016-07-05","Score":"Missing","FilterCategories":["Demographics","Economics","Transportation","Government"],"Status":"","SubResources":[],"Icons":[]},{"Name":{"Label":"IBRD Statement of Loans","URL":"https:\/\/datarepository.wolframcloud.com\/resources\/11d91b4a-ed29-4c06-b33a-24a6a4b4e920\/"},"UUID":"11d91b4a-ed29-4c06-b33a-24a6a4b4e920","Description":"Data on International Bank for Reconstruction and Development loans","ReleaseDate":"2015-11-26","Score":"Missing","FilterCategories":["Economics"],"Status":"","SubResources":[],"Icons":[]},{"Name":{"Label":"IMF World Economic Outlook","URL":"https:\/\/datarepository.wolframcloud.com\/resources\/3660a58f-c155-4640-b16b-49be25f25648\/"},"UUID":"3660a58f-c155-4640-b16b-49be25f25648","Description":"Selected macroeconomic data series from the International Monetary Fund","ReleaseDate":"2017-08-28","Score":"Missing","FilterCategories":["Economics","Statistics"],"Status":"","SubResources":[],"Icons":[]},{"Name":{"Label":"Negative Binomial Distributed Accident Data","URL":"https:\/\/datarepository.wolframcloud.com\/resources\/f0c80de3-d773-4917-ae05-5599ef7de4d2\/"},"UUID":"f0c80de3-d773-4917-ae05-5599ef7de4d2","Description":"Number of accidents experienced by employees in a factory in a year","ReleaseDate":"2022-10-14","Score":"Missing","FilterCategories":["Economics","Statistics"],"Status":"","SubResources":[],"Icons":[]},{"Name":{"Label":"New Orleans Slave Sales 1856-1861","URL":"https:\/\/datarepository.wolframcloud.com\/resources\/f372fe55-1809-4c2d-bf0c-3fbae99d41cf\/"},"UUID":"f372fe55-1809-4c2d-bf0c-3fbae99d41cf","Description":"Slave sales recorded by the New Orleans register of conveyance, October 1856 to August 1861","ReleaseDate":"2016-10-22","Score":"Missing","FilterCategories":["Economics","Human Activities"],"Status":"","SubResources":[],"Icons":[]},{"Name":{"Label":"NYC Jobs, Aug 2015 - Aug 2016","URL":"https:\/\/datarepository.wolframcloud.com\/resources\/129df514-301f-4f21-9202-29ed255510b2\/"},"UUID":"129df514-301f-4f21-9202-29ed255510b2","Description":"Information about NYC jobs for Aug. 2015 - Aug. 2016","ReleaseDate":"2016-09-08","Score":"Missing","FilterCategories":["Economics"],"Status":"","SubResources":[],"Icons":[]},{"Name":{"Label":"Senators of the 116th Congress","URL":"https:\/\/datarepository.wolframcloud.com\/resources\/44388285-c744-4c4f-a704-fd70bbb0bc33\/"},"UUID":"44388285-c744-4c4f-a704-fd70bbb0bc33","Description":"Dataset for the U.S. Senators of the 116th Congress","ReleaseDate":"2020-04-30","Score":"Missing","FilterCategories":["Economics","Government","Politics"],"Status":"","SubResources":[],"Icons":[]},{"Name":{"Label":"State Government Finances 2013","URL":"https:\/\/datarepository.wolframcloud.com\/resources\/aea2abb5-c61d-4f6c-9f3b-819b5a97c3c0\/"},"UUID":"aea2abb5-c61d-4f6c-9f3b-819b5a97c3c0","Description":"U.S. Census Bureau, 2013 Annual Survey of State Government Finances","ReleaseDate":"2016-02-14","Score":"Missing","FilterCategories":["Government","Economics"],"Status":"","SubResources":[],"Icons":[]},{"Name":{"Label":"The Big Mac Index","URL":"https:\/\/datarepository.wolframcloud.com\/resources\/fbca04ce-2507-4a43-b018-3a84f19916e8\/"},"UUID":"fbca04ce-2507-4a43-b018-3a84f19916e8","Description":"The Big Mac index, published by The Economist from 2000 to 2018.","ReleaseDate":"2018-12-05","Score":"Missing","FilterCategories":["Economics"],"Status":"","SubResources":[],"Icons":[]},{"Name":{"Label":"Total Wildland Fires and Acres (1926-2019)","URL":"https:\/\/datarepository.wolframcloud.com\/resources\/ef2219f4-4dfc-4682-9afb-b3e01ac0b78e\/"},"UUID":"ef2219f4-4dfc-4682-9afb-b3e01ac0b78e","Description":"Annual wildland fire statistics for federal and state agencies","ReleaseDate":"2020-09-15","Score":"Missing","FilterCategories":["Agriculture","Earth Science","Economics","Government","History","Human Activities","Politics"],"Status":"","SubResources":[],"Icons":[]},{"Name":{"Label":"US Census Mean Household Income Data","URL":"https:\/\/datarepository.wolframcloud.com\/resources\/0733f86a-03bd-4c0a-a6cf-a9a9b500657a\/"},"UUID":"0733f86a-03bd-4c0a-a6cf-a9a9b500657a","Description":"Data gives the average household income for different income groups (for each fifth and the top 5%) in the United States over the period 1967-2017","ReleaseDate":"2020-08-25","Score":"Missing","FilterCategories":["Demographics","Economics","Government","Politics","Sociology"],"Status":"","SubResources":[],"Icons":[]},{"Name":{"Label":"US Federal Outlays by Agency","URL":"https:\/\/datarepository.wolframcloud.com\/resources\/25c95bd1-fd3b-4388-9bdc-a1cc52b136ea\/"},"UUID":"25c95bd1-fd3b-4388-9bdc-a1cc52b136ea","Description":"Federal government outlays by agency, 1962-2020","ReleaseDate":"2016-01-04","Score":"Missing","FilterCategories":["Government","Economics"],"Status":"","SubResources":[],"Icons":[]},{"Name":{"Label":"US Federal Reserve Systems","URL":"https:\/\/datarepository.wolframcloud.com\/resources\/b8276f62-f4db-4e48-9757-4f9540408b91\/"},"UUID":"b8276f62-f4db-4e48-9757-4f9540408b91","Description":"Detailed location information for all U.S. Federal Reserve Banks and Branches","ReleaseDate":"2017-01-25","Score":"Missing","FilterCategories":["Geography","Economics","Human Activities"],"Status":"","SubResources":[],"Icons":[]},{"Name":{"Label":"US Hurricane Losses","URL":"https:\/\/datarepository.wolframcloud.com\/resources\/c77a52c2-ef21-424d-a7a3-e1ca59bf9573\/"},"UUID":"c77a52c2-ef21-424d-a7a3-e1ca59bf9573","Description":"U.S. losses due to hurricanes in millions of U.S. Dollars","ReleaseDate":"2017-07-19","Score":"Missing","FilterCategories":["Economics"],"Status":"","SubResources":[],"Icons":[]},{"Name":{"Label":"US State Income","URL":"https:\/\/datarepository.wolframcloud.com\/resources\/f8764454-ab8b-4cb9-9617-3dcf3acb49e4\/"},"UUID":"f8764454-ab8b-4cb9-9617-3dcf3acb49e4","Description":"United States per capita income by state","ReleaseDate":"2016-02-09","Score":"Missing","FilterCategories":["Economics"],"Status":"","SubResources":[],"Icons":[]}],"SortingStrategies":["Name","Date"],"DefaultSortingStrategy":"Name"}